[
  {
    "id": 1,
    "name": "Product A",
    "price": 120000
  },
  {
    "id": 2,
    "name": "Product B",
    "price": 100
  },
  {
    "id": 3,
    "name": "Product C",
    "price": 60
  },
  {
    "id": 4,
    "name": "Updated Product D",
    "price": 120
  },
  {
    "id": 5,
    "name": "Product E",
    "price": 1000
  },
  {
    "id": 6,
    "name": "Product F",
    "price": 9500
  },
  {
    "id": 7,
    "name": "Product G",
    "price": 300
  },
  {
    "id": 8,
    "name": "Product H",
    "price": 3000
  },
  {
    "id": 9,
    "name": "Product I",
    "price": 5
  },
  {
    "id": 10,
    "name": "Product J",
    "price": 20
  },
  {
    "id": 11,
    "name": "Updated Product K",
    "price": 155
  }
]